{
  "categories": [
    {
      "name": "Película",
      "preguntas": [
        {
          "preg": "¿Quién es el famoso actor que viene a Comic Con PY?",
          "resp": [
            {
              "rta": "Jeffrey Dean Morgan",
              "correcta": false
            },
            {
              "rta": "Andrew Lincoln",
              "correcta": false
            },
            {
              "rta": "Ross Marquand",
              "correcta": true
            }
          ]
        },
        {
          "preg": "¿Cuántas temporadas tiene Games Of Thrones?",
          "resp": [
            {
              "rta": "7",
              "correcta": false
            },
            {
              "rta": "8",
              "correcta": true
            },
            {
              "rta": "10",
              "correcta": false
            }
          ]
        }
      ]
    },
    {
      "name": "Personajes",
      "preguntas": [
        {
          "preg": "¿A qué persona asesinan a los padres y busca venganza?",
          "resp": [
            {
              "rta": "Capitán América",
              "correcta": false
            },
            {
              "rta": "Batman",
              "correcta": true
            },
            {
              "rta": "Flash",
              "correcta": false
            }
          ]
        },
        {
          "preg": "¿Qué personaje utiliza flechas en los cómics de DC?",
          "resp": [
            {
              "rta": "Flash",
              "correcta": false
            },
            {
              "rta": "La Mujer Maravilla",
              "correcta": false
            },
            {
              "rta": "Arrow",
              "correcta": true
            }
          ]
        }
      ]
    },
    {
      "name": "COMIC",
      "preguntas": [
        {
          "preg": "¿Cuál fue el primer personaje del comic?",
          "resp": [
            {
              "rta": "Antorcha Humana",
              "correcta": true
            },
            {
              "rta": "Capitán América",
              "correcta": false
            },
            {
              "rta": "Iron Man",
              "correcta": false
            }
          ]
        },
        {
          "preg": "¿Qué personajes creó Stan Lee?",
          "resp": [
            {
              "rta": "Aquaman, Spider-Man",
              "correcta": false
            },
            {
              "rta": "Spider-Man, Daredevli",
              "correcta": true
            },
            {
              "rta": " Los 4 fantasticos, Batman",
              "correcta": false
            }
          ]
        }
      ]
    },
    {
      "name": " Ilustración",
      "preguntas": [
        {
          "preg": " ¿Cómo se llamaba el primer dibujo de comic?",
          "resp": [
            {
              "rta": "BLU KID",
              "correcta": false
            },
            {
              "rta": "WILD KID",
              "correcta": false
            },
            {
              "rta": "YELLOW KID",
              "correcta": true
            }
          ]
        },
        {
          "preg": "¿En qué año apareció la primera Ilustración? ",
          "resp": [
            {
              "rta": "1886",
              "correcta": false
            },
            {
              "rta": "1895",
              "correcta": true
            },
            {
              "rta": "1900",
              "correcta": false
            }
          ]
        }
      ]
    },
    {
      "name": "Cosplay",
      "preguntas": [
        {
          "preg": "¿En qué pais se hace la conveción más grande del mundo?",
          "resp": [
            {
              "rta": "Taiwan",
              "correcta": false
            },
            {
              "rta": "Singapur",
              "correcta": false
            },
            {
              "rta": "Tokio",
              "correcta": true
            }
          ]
        },
        {
          "preg": "¿Quién es la mejor cosplay del mundo?",
          "resp": [
            {
              "rta": "Ena Korin",
              "correcta": false
            },
            {
              "rta": "Jessica Nigri",
              "correcta": true
            },
            {
              "rta": "Enji Night",
              "correcta": false
            }
          ]
        }
      ]
    }
  ]
}